setup.cfg
setup.py
notebook_ok_extension.egg-info/PKG-INFO
notebook_ok_extension.egg-info/SOURCES.txt
notebook_ok_extension.egg-info/dependency_links.txt
notebook_ok_extension.egg-info/requires.txt
notebook_ok_extension.egg-info/top_level.txt
ok/__init__.py