Metadata-Version: 1.1
Name: notebook-ok-extension
Version: 0.1.1
Summary: An extension of the Jupyter Notebook that integrates testing with OK client.
Home-page: https://github.com/dsten/notebook-ok-extension
Author: Alvin Wan
Author-email: hi@alvinwan.com
License: UNKNOWN
Download-URL: https://github.com/dsten/notebook-ok-extension/archive/0.1.1.zip
Keywords: data,tools,berkeley
Platform: UNKNOWN
Classifier: Programming Language :: Python
